LICENSE
MANIFEST.in
README.md
setup.py
assests/version.json
kivi/__init__.py
kivi/erros.py
kivi/pkg.py
kivi.py.egg-info/PKG-INFO
kivi.py.egg-info/SOURCES.txt
kivi.py.egg-info/dependency_links.txt
kivi.py.egg-info/requires.txt
kivi.py.egg-info/top_level.txt
kivi/extensions/__init__.py
kivi/extensions/converter.py
kivi/extensions/handlers.py
kivi/extensions/tools.py