Metadata-Version: 2.1
Name: kivi.py
Version: 0.1.2
Summary: A simple key-value database
Home-page: https://github.com/Itz-fork/kivi.py
Download-URL: https://github.com/Itz-fork/kivi.py/releases/tag/kivi.py-pypi-0.1.2
Author: Itz-fork
Author-email: git.itzfork@gmail.com
License: MIT
Keywords: databse,key-value,key-value database,kivi.py
Classifier: Development Status :: 5 - Production/Stable
Classifier: Intended Audience :: Developers
Classifier: Topic :: Education
Classifier: License :: OSI Approved :: MIT License
Classifier: Programming Language :: Python :: 3
Classifier: Programming Language :: Python :: 3.4
Classifier: Programming Language :: Python :: 3.5
Classifier: Programming Language :: Python :: 3.6
Classifier: Programming Language :: Python :: 3.9
Classifier: Programming Language :: Python :: 3.10
Classifier: Programming Language :: Python :: 3.11
License-File: LICENSE
